rtl/subtractor.sv
`timescale 1ns / 1ps

module subtractor (
    input  logic [7:0] credit,
    input  logic [7:0] price,
    output logic [7:0] change
);

    assign change = credit - price;

endmodule

rtl/comparator.sv
`timescale 1ns / 1ps

module comparator (
    input  logic [7:0] credit,
    input  logic [7:0] price,
    input  logic [7:0] stock,
    output logic can_sell
);

    assign can_sell = (credit >= price) && (stock > 0);

endmodule

rtl/memory.sv
`timescale 1ns / 1ps

module memory (
    input  logic clk,
    input  logic rst,
    input  logic mem_write,
    input  logic cancel_collect,
    input  logic [1:0] sel_item,
    output logic [7:0] price,
    output logic [7:0] stock
);

    logic [7:0] prices_array [0:3];
    logic [7:0] stocks_array [0:3];

    assign price = prices_array[sel_item];
    assign stock = stocks_array[sel_item];

    always_ff @(posedge clk or posedge rst) begin
        if (rst) begin
            prices_array[0] <= 8'd25;  
            stocks_array[0] <= 8'd5;   

            prices_array[1] <= 8'd50;  
            stocks_array[1] <= 8'd5;   

            prices_array[2] <= 8'd75;  
            stocks_array[2] <= 8'd3;   

            prices_array[3] <= 8'd100; 
            stocks_array[3] <= 8'd2;   
            
        end else begin
            if (mem_write && stocks_array[sel_item] > 8'd0) begin
                stocks_array[sel_item] <= stocks_array[sel_item] - 8'd1;
            end
            
            if (cancel_collect) begin
                prices_array <= '{default: 8'd0};
            end else begin
            prices_array[0] <= 8'd25;    

            prices_array[1] <= 8'd50;  


            prices_array[2] <= 8'd75;  
  

            prices_array[3] <= 8'd100; 
     
            end
        end
    end

endmodule

rtl/credit_reg.sv
`timescale 1ns / 1ps

module credit_reg (
    input  logic clk,
    input  logic rst,
    input  logic clear,
    input  logic credit_load,
    input  logic [7:0] coin_value,
    output logic [7:0] credit
);

    always_ff @(posedge clk or posedge rst) begin
        if (rst) begin
            credit <= 8'b0;
        end else begin
            
            if (clear) begin
                credit <= 8'b0;
            end 
            else if (credit_load) begin
                credit <= credit + coin_value;
            end
        end
    end

endmodule

rtl/control_unit.sv
`timescale 1ns / 1ps

import vending_pkg::*; 

module control_unit (
    input logic clk,
    input logic rst,

    input logic [1:0] coin_in,
    input logic confirm,
    input logic cancel,

    input logic can_sell,

    output logic credit_load,
    output logic clear,
    output logic mem_write,
    output logic sel_change,
    output logic load_change,
    output logic cancel_collect,
    output logic dispense,
    output logic error_out,
    output state_t state_out
);

    state_t current_state, next_state;

    always_ff @(posedge clk or posedge rst) begin
        if (rst) begin
            current_state <= IDLE;
        end else begin
            current_state <= next_state;
        end
    end

    assign state_out = current_state;

    always_comb begin
        next_state = current_state; 

        case (current_state)
            IDLE: begin
                if (coin_in != 2'b00) 
                    next_state = COLLECT;
            end
            
            COLLECT: begin
                if (cancel) begin
                    next_state = CHANGE;
                end else if (confirm) begin
                    next_state = CHECK;
                end
            end
            
            CHECK: begin
                if (can_sell) 
                    next_state = DISPENSE;
                else 
                    next_state = ERROR;
            end
            
            DISPENSE: begin
                next_state = CHANGE;
            end
            
            CHANGE: begin
                next_state = IDLE;
            end
            
            ERROR: begin
                if (cancel)
                    next_state = IDLE;
                else
                    next_state = ERROR;
            end
            
            default: next_state = IDLE;
        endcase
    end

    always_comb begin
        credit_load    = 1'b0;
        clear          = 1'b0;
        mem_write      = 1'b0;
        sel_change     = 1'b0;
        load_change    = 1'b0;
        cancel_collect = 1'b0;
        dispense       = 1'b0;
        error_out      = 1'b0;

        case (current_state)
            IDLE: begin
                if (coin_in != 2'b00) begin
                    credit_load = 1'b1;
                end
            end
            
            COLLECT: begin
                if (coin_in != 2'b00) begin
                    credit_load = 1'b1;
                end
                if (cancel) begin
                    cancel_collect = 1'b1;
                end
            end
            
            CHECK: begin

            end
            
            DISPENSE: begin
                dispense    = 1'b1;
                mem_write   = 1'b1;
                load_change = 1'b1;
                sel_change  = 1'b0; 
            end
            
            CHANGE: begin
                clear = 1'b1; 
                if (cancel_collect) begin
                    load_change = 1'b1;
                    sel_change  = 1'b1;
                end
            end
            
            ERROR: begin
                error_out   = 1'b1;
                sel_change  = 1'b1; 
                load_change = 1'b1;
                if (cancel) begin
                    clear = 1'b1;
                end
            end
        endcase
    end

endmodule

rtl/vending_top.sv
`timescale 1ns / 1ps

import vending_pkg::*;

module vending_top (
    input  logic clk,
    input  logic rst,
    input  logic [1:0] coin_in,
    input  logic [1:0] sel_item,
    input  logic confirm,
    input  logic cancel,

    output logic dispense,
    output logic error_out,
    output logic [7:0] change_out,
    output logic [7:0] display,
    output state_t state_out
);

    logic [7:0] coin_value;
    logic [7:0] credit;
    logic [7:0] price;
    logic [7:0] stock;
    logic [7:0] change_wire;
    logic [7:0] mux_out;

    logic can_sell;
    logic credit_load;
    logic clear;
    logic mem_write;
    logic sel_change;
    logic load_change;
    logic cancel_collect;

    assign display = credit;

    always_comb begin
        case (coin_in)
            2'b01: coin_value = 8'd25;
            2'b10: coin_value = 8'd50;
            2'b11: coin_value = 8'd100;
            default: coin_value = 8'd0;
        endcase
    end

    
    assign mux_out = (sel_change || state_out == CHANGE && cancel) ? credit : change_wire;

    always_ff @(posedge clk or posedge rst) begin
        if (rst) begin
            change_out <= 8'b0;
        end else if (load_change || (state_out == COLLECT && cancel)) begin
            change_out <= (state_out == COLLECT && cancel) ? credit : mux_out;
        end
    end

    control_unit u_fsm (
        .clk (clk),
        .rst (rst),
        .coin_in (coin_in),
        .confirm (confirm),
        .cancel (cancel),
        .can_sell (can_sell),
        .credit_load (credit_load),
        .clear (clear),
        .mem_write (mem_write),
        .sel_change (sel_change),
        .load_change (load_change),
        .dispense (dispense),
        .error_out (error_out),
        .state_out (state_out),
        .cancel_collect(cancel_collect)
    );

    credit_reg u_credit_reg (
        .clk (clk),
        .rst (rst),
        .clear (clear),
        .credit_load (credit_load),
        .coin_value (coin_value),
        .credit (credit)
    );

    memory u_memory (
        .clk (clk),
        .rst (rst),
        .mem_write (mem_write),
        .sel_item (sel_item),
        .price (price),
        .stock (stock)
    );

    comparator u_comparator (
        .credit (credit),
        .price (price),
        .stock (stock),
        .can_sell (can_sell)
    );

    subtractor u_subtractor (
        .credit (credit),
        .price (price),
        .change (change_wire)
    );

endmodule

sim/tb_vending.sv
`timescale 1ns / 1ps

module vending_tb;

    // Encoding dos estados da FSM:
    localparam ST_IDLE = 3'b000;
    localparam ST_COLLECT = 3'b001;
    localparam ST_CHECK = 3'b010;
    localparam ST_DISPENSE = 3'b011;
    localparam ST_CHANGE = 3'b100;
    localparam ST_ERROR = 3'b101;

    logic clk;
    logic reset;
    logic [1:0] coin_in;
    logic [1:0] sel_item;
    logic confirm;
    logic cancel;

    logic dispense;
    logic error_out;
    logic [7:0] change_out;
    logic [7:0] display;
    logic [2:0] state_out;

    vending_top dut (
        .clk(clk),
        .rst(reset),
        .coin_in(coin_in),
        .sel_item(sel_item),
        .confirm(confirm),
        .cancel(cancel),
        .dispense(dispense),
        .error_out(error_out),
        .change_out(change_out),
        .display(display),
        .state_out(state_out)
    );

    initial begin
        clk = 0;
        forever #5 clk = ~clk;
    end

    initial begin
        #10000;
        $display("[FAIL] A simulacao excedeu 10.000ns, possivel FSM travada");
        $finish;
    end

    task apply_coin(input [1:0] value);
        begin
            @(posedge clk);
            coin_in = value;
            @(posedge clk);
            coin_in = 2'b00;
            @(posedge clk);
        end
    endtask

    task buy_item(input [1:0] item, input [1:0] coins []);
        begin
            sel_item = item;
            foreach (coins[i]) begin
                apply_coin(coins[i]);
            end
            confirm = 1;
            @(posedge clk);
            @(posedge clk);
            confirm = 0;
            @(posedge clk);
        end
    endtask

    task check(input [7:0] expected, input [7:0] actual, input string label);
        begin
            if (expected === actual)
                $display("[PASS] %s", label);
            else
                $display("[FAIL] %s | Esperado: %0d, obtido: %0d", label, expected, actual);
        end
    endtask

    task wait_until_state(input [2:0] target_state);
        begin
            while (state_out !== target_state) begin
                @(posedge clk);
            end
        end
    endtask

    task wait_until_idle();
        begin
            wait_until_state(ST_IDLE);
        end
    endtask

    task recover_from_error();
        begin
            @(posedge clk);
            cancel = 1;
            @(posedge clk);
            @(posedge clk);
            cancel = 0;
            
            wait_until_idle();
        end
    endtask

    initial begin
        $dumpfile("vending_tb.vcd");
        $dumpvars(0, vending_tb);

        coin_in = 2'b00;
        sel_item = 2'b00;
        confirm = 0;
        cancel = 0;

        reset = 1;
        repeat (2) @(posedge clk);
        reset = 0;
        wait_until_idle();

        // Cenário 1: compra bem-sucedida com troco:
        buy_item(2'b00, '{2'b11});
        wait_until_state(ST_DISPENSE);
        check(1, dispense, "Cenario 1: dispense = 1");
        wait_until_state(ST_CHANGE);
        check(75, change_out, "Cenario 1: troco = 75");
        wait_until_idle();
        check(0, display, "Cenario 1: credito = 0 ao final");

        // Cenário 2: crédito insuficiente:
        buy_item(2'b11, '{2'b01});
        wait_until_state(ST_ERROR);
        check(1, error_out, "Cenario 2: ERROR = 1");
        check(ST_ERROR, state_out, "Cenario 2: FSM em ERROR");
        recover_from_error();

        // Cenário 3: cancelamento:
        apply_coin(2'b11);
        apply_coin(2'b11);
        @(posedge clk);
        cancel = 1;
        @(posedge clk);
        @(posedge clk);
        cancel = 0;

        wait_until_idle();
        check(200, change_out, "Cenario 3: cancel troco = 200");
        check(0, display, "Cenario 3: credito = 0 apos cancelamento");
        check(ST_IDLE, state_out, "Cenario 3: FSM retorna a IDLE");

        // Cenário 4: estoque zerado:
        for (int i = 1; i <= 4; i++) begin
            buy_item(2'b00, '{2'b11});
            wait_until_idle();
        end
        buy_item(2'b00, '{2'b11});
        wait_until_state(ST_ERROR);
        check(1, error_out, "Cenario 4: ERROR estoque vazio = 1");
        check(ST_ERROR, state_out, "Cenario 4: FSM em ERROR (sem estoque)");
        recover_from_error();

        $display("Todos os cenarios foram validados!");
        $finish;
    end

endmodule

sim/vending_tb.vcd
$date
	Fri Jul 10 06:33:15 2026
$end
$version
	ModelSim Version 10.5b
$end
$timescale
	1ps
$end

$scope module vending_tb $end
$var parameter 3 ! ST_IDLE $end
$var parameter 3 " ST_COLLECT $end
$var parameter 3 # ST_CHECK $end
$var parameter 3 $ ST_DISPENSE $end
$var parameter 3 % ST_CHANGE $end
$var parameter 3 & ST_ERROR $end
$var reg 1 ' clk $end
$var reg 1 ( reset $end
$var reg 2 ) coin_in [1:0] $end
$var reg 2 * sel_item [1:0] $end
$var reg 1 + confirm $end
$var reg 1 , cancel $end
$var reg 1 - dispense $end
$var reg 1 . error_out $end
$var reg 8 / change_out [7:0] $end
$var reg 8 0 display [7:0] $end
$var reg 3 1 state_out [2:0] $end

$scope task apply_coin $end
$var reg 2 2 value [1:0] $end
$upscope $end

$scope task buy_item $end
$var reg 2 3 item [1:0] $end
$upscope $end

$scope task check $end
$var reg 8 4 expected [7:0] $end
$var reg 8 5 actual [7:0] $end
$upscope $end

$scope task wait_until_state $end
$var reg 3 6 target_state [2:0] $end
$upscope $end

$scope task wait_until_idle $end
$upscope $end

$scope task recover_from_error $end
$upscope $end

$scope module dut $end
$var wire 1 7 clk $end
$var wire 1 8 rst $end
$var wire 1 9 coin_in [1] $end
$var wire 1 : coin_in [0] $end
$var wire 1 ; sel_item [1] $end
$var wire 1 < sel_item [0] $end
$var wire 1 = confirm $end
$var wire 1 > cancel $end
$var reg 1 ? dispense $end
$var reg 1 @ error_out $end
$var reg 8 A change_out [7:0] $end
$var reg 8 B display [7:0] $end
$var reg 3 C state_out [2:0] $end
$var reg 8 D coin_value [7:0] $end
$var reg 8 E credit [7:0] $end
$var reg 8 F price [7:0] $end
$var reg 8 G stock [7:0] $end
$var reg 8 H change_wire [7:0] $end
$var reg 8 I mux_out [7:0] $end
$var reg 1 J can_sell $end
$var reg 1 K credit_load $end
$var reg 1 L clear $end
$var reg 1 M mem_write $end
$var reg 1 N sel_change $end
$var reg 1 O load_change $end
$var reg 1 P cancel_collect $end

$scope module u_fsm $end
$var wire 1 7 clk $end
$var wire 1 8 rst $end
$var wire 1 9 coin_in [1] $end
$var wire 1 : coin_in [0] $end
$var wire 1 = confirm $end
$var wire 1 > cancel $end
$var wire 1 Q can_sell $end
$var reg 1 R credit_load $end
$var reg 1 S clear $end
$var reg 1 T mem_write $end
$var reg 1 U sel_change $end
$var reg 1 V load_change $end
$var reg 1 W cancel_collect $end
$var reg 1 X dispense $end
$var reg 1 Y error_out $end
$var reg 3 Z state_out [2:0] $end
$var reg 3 [ current_state [2:0] $end
$var reg 3 \ next_state [2:0] $end
$upscope $end

$scope module u_credit_reg $end
$var wire 1 7 clk $end
$var wire 1 8 rst $end
$var wire 1 ] clear $end
$var wire 1 ^ credit_load $end
$var wire 1 _ coin_value [7] $end
$var wire 1 ` coin_value [6] $end
$var wire 1 a coin_value [5] $end
$var wire 1 b coin_value [4] $end
$var wire 1 c coin_value [3] $end
$var wire 1 d coin_value [2] $end
$var wire 1 e coin_value [1] $end
$var wire 1 f coin_value [0] $end
$var reg 8 g credit [7:0] $end
$upscope $end

$scope module u_memory $end
$var wire 1 7 clk $end
$var wire 1 8 rst $end
$var wire 1 h mem_write $end
$var wire 1 i cancel_collect $end
$var wire 1 ; sel_item [1] $end
$var wire 1 < sel_item [0] $end
$var reg 8 j price [7:0] $end
$var reg 8 k stock [7:0] $end
$upscope $end

$scope module u_comparator $end
$var wire 1 l credit [7] $end
$var wire 1 m credit [6] $end
$var wire 1 n credit [5] $end
$var wire 1 o credit [4] $end
$var wire 1 p credit [3] $end
$var wire 1 q credit [2] $end
$var wire 1 r credit [1] $end
$var wire 1 s credit [0] $end
$var wire 1 t price [7] $end
$var wire 1 u price [6] $end
$var wire 1 v price [5] $end
$var wire 1 w price [4] $end
$var wire 1 x price [3] $end
$var wire 1 y price [2] $end
$var wire 1 z price [1] $end
$var wire 1 { price [0] $end
$var wire 1 | stock [7] $end
$var wire 1 } stock [6] $end
$var wire 1 ~ stock [5] $end
$var wire 1 !! stock [4] $end
$var wire 1 "! stock [3] $end
$var wire 1 #! stock [2] $end
$var wire 1 $! stock [1] $end
$var wire 1 %! stock [0] $end
$var reg 1 &! can_sell $end
$upscope $end

$scope module u_subtractor $end
$var wire 1 '! credit [7] $end
$var wire 1 (! credit [6] $end
$var wire 1 )! credit [5] $end
$var wire 1 *! credit [4] $end
$var wire 1 +! credit [3] $end
$var wire 1 ,! credit [2] $end
$var wire 1 -! credit [1] $end
$var wire 1 .! credit [0] $end
$var wire 1 /! price [7] $end
$var wire 1 0! price [6] $end
$var wire 1 1! price [5] $end
$var wire 1 2! price [4] $end
$var wire 1 3! price [3] $end
$var wire 1 4! price [2] $end
$var wire 1 5! price [1] $end
$var wire 1 6! price [0] $end
$var reg 8 7! change [7:0] $end
$upscope $end
$upscope $end
$upscope $end
$enddefinitions $end
#0
$dumpvars
0'
1(
b0 )
b0 *
0+
0,
0-
0.
b0 /
b0 0
b0 1
0?
0@
b0 A
b0 B
b0 C
b0 D
b0 E
b11001 F
b101 G
b11100111 H
b11100111 I
0J
0K
0L
0M
0N
0O
0P
0R
0S
0T
0U
0V
0W
0X
0Y
b0 Z
b0 [
b0 \
b0 g
b11001 j
b101 k
0&!
b11100111 7!
bx 2
bx 3
bx 4
bx 5
bx 6
b0 !
b1 "
b10 #
b11 $
b100 %
b101 &
07
18
0:
09
0<
0;
0=
0>
0Q
0]
0^
0f
0e
0d
0c
0b
0a
0`
0_
0h
zi
0s
0r
0q
0p
0o
0n
0m
0l
1{
0z
0y
1x
1w
0v
0u
0t
1%!
0$!
1#!
0"!
0!!
0~
0}
0|
0.!
0-!
0,!
0+!
0*!
0)!
0(!
0'!
16!
05!
04!
13!
12!
01!
00!
0/!
$end
#5000
1'
17
#10000
0'
07
#15000
1'
17
0(
b0 6
b0 3
b11 2
08
#20000
0'
07
#25000
1'
17
b11 )
1:
19
b1100100 D
b1 \
1R
1K
1d
1a
1`
1^
#30000
0'
07
#35000
1'
17
b0 )
0:
09
b0 D
b0 \
0R
0K
0d
0a
0`
0^
b1 [
b1100100 g
b1100100 E
b1 Z
b1 C
b1100100 B
1q
1n
1m
1,!
1)!
1(!
b1001011 7!
1&!
b1100100 0
b1 1
1J
b1001011 H
b1001011 I
1Q
b1 \
#40000
0'
07
#45000
1'
17
1+
1=
b10 \
#50000
0'
07
#55000
1'
17
b10 [
b10 Z
b10 C
b10 1
b11 \
#60000
0'
07
#65000
1'
17
0+
0=
b10 \
b11 \
b11 [
b11 Z
b11 C
b11 1
b100 \
1X
1T
1V
1O
1M
1?
1-
1h
#70000
0'
07
#75000
1'
17
b11 6
b1 4
b1 5
b100 6
b1001011 A
b100 [
b100 k
b100 Z
b1001011 /
b100 C
b100 G
b100 1
0%!
b0 \
0T
0V
0X
1S
1L
0?
0O
0M
0-
1]
0h
#80000
0'
07
#85000
1'
17
b1001011 4
b1001011 5
b0 6
b0 [
b0 g
b0 E
b0 Z
b0 C
b0 B
0q
0n
0m
0,!
0)!
0(!
b11100111 7!
0&!
b0 0
b0 1
0J
b11100111 H
b11100111 I
0Q
0S
0L
0]
#90000
0'
07
#95000
1'
17
b0 4
b0 5
b11 3
b11 *
b1 2
1<
1;
b1100100 j
b10 k
b10 G
b1100100 F
0{
1y
0x
0w
1v
1u
06!
14!
03!
02!
11!
10!
1$!
0#!
b10011100 7!
b10011100 H
b10011100 I
#100000
0'
07
#105000
1'
17
b1 )
1:
b11001 D
b1 \
1R
1K
1f
1c
1b
1^
#110000
0'
07
#115000
1'
17
b0 )
0:
b0 D
b0 \
0R
0K
0f
0c
0b
0^
b1 [
b11001 g
b11001 E
b1 Z
b1 C
b11001 B
1s
1p
1o
1.!
1+!
1*!
b10110101 7!
b11001 0
b1 1
b10110101 H
b10110101 I
b1 \
#120000
0'
07
#125000
1'
17
1+
1=
b10 \
#130000
0'
07
#135000
1'
17
b10 [
b10 Z
b10 C
b10 1
b101 \
#140000
0'
07
#145000
1'
17
0+
0=
b10 \
b101 \
b101 [
b101 Z
b101 C
b101 1
1Y
1U
1V
1O
1N
1@
1.
b11001 I
#150000
0'
07
#155000
1'
17
b101 6
b1 4
b1 5
b101 4
b101 5
b11001 A
b11001 /
#160000
0'
07
#165000
1'
17
1,
1>
b0 \
0U
0V
0Y
1Y
1U
1V
1S
1L
1]
#170000
0'
07
#175000
1'
17
b0 [
b0 g
b0 E
b0 Z
b0 C
b0 B
b0 I
0s
0p
0o
0.!
0+!
0*!
b10011100 7!
b0 0
b0 1
b10011100 H
0S
0U
0V
0Y
0@
0O
0N
0L
b10011100 I
0.
0]
#180000
0'
07
#185000
1'
17
0,
b0 6
b11 2
0>
#190000
0'
07
#195000
1'
17
b11 )
1:
19
b1100100 D
b1 \
1R
1K
1d
1a
1`
1^
#200000
0'
07
#205000
1'
17
b0 )
0:
09
b0 D
b0 \
0R
0K
0d
0a
0`
0^
b1 [
b1100100 g
b1100100 E
b1 Z
b1 C
b1100100 B
1q
1n
1m
1,!
1)!
1(!
b0 7!
1&!
b1100100 0
b1 1
1J
b0 H
b0 I
1Q
b1 \
#210000
0'
07
#215000
1'
17
#220000
0'
07
#225000
1'
17
b11 )
1:
19
b1100100 D
1R
1K
1d
1a
1`
1^
#230000
0'
07
#235000
1'
17
b0 )
0:
09
b0 D
0R
0K
0d
0a
0`
0^
b11001000 g
b11001000 E
b11001000 B
0q
1p
0n
1l
0,!
1+!
0)!
1'!
b1100100 7!
b11001000 0
b1100100 H
b1100100 I
#240000
0'
07
#245000
1'
17
#250000
0'
07
#255000
1'
17
1,
1>
b100 \
1W
1P
#260000
0'
07
#265000
1'
17
b11001000 A
b100 [
b100 Z
b11001000 /
b100 C
b100 1
b11001000 I
b0 \
0W
1S
1L
0P
1]
#270000
0'
07
#275000
1'
17
0,
0>
b1100100 I
b100 \
b0 \
0S
1S
b0 [
b0 g
b0 E
b0 Z
b0 C
b0 B
0p
0m
0l
0+!
0(!
0'!
b10011100 7!
0&!
b0 0
b0 1
0J
b10011100 H
b10011100 I
0Q
0S
0L
0]
#280000
0'
07
#285000
1'
17
b11001000 4
b11001000 5
b0 4
b0 5
b0 3
b0 *
0<
0;
b11001 j
b100 k
b100 G
b11001 F
1{
0y
1x
1w
0v
0u
16!
04!
13!
12!
01!
00!
0$!
1#!
b11100111 7!
b11100111 H
b11100111 I
#290000
0'
07
#295000
1'
17
b11 )
1:
19
b1100100 D
b1 \
1R
1K
1d
1a
1`
1^
#300000
0'
07
#305000
1'
17
b0 )
0:
09
b0 D
b0 \
0R
0K
0d
0a
0`
0^
b1 [
b1100100 g
b1100100 E
b1 Z
b1 C
b1100100 B
1q
1n
1m
1,!
1)!
1(!
b1001011 7!
1&!
b1100100 0
b1 1
1J
b1001011 H
b1001011 I
1Q
b1 \
#310000
0'
07
#315000
1'
17
1+
1=
b10 \
#320000
0'
07
#325000
1'
17
b10 [
b10 Z
b10 C
b10 1
b11 \
#330000
0'
07
#335000
1'
17
0+
0=
b10 \
b11 \
b11 [
b11 Z
b11 C
b11 1
b100 \
1X
1T
1V
1O
1M
1?
1-
1h
#340000
0'
07
#345000
1'
17
b1001011 A
b100 [
b11 k
b100 Z
b1001011 /
b100 C
b11 G
b100 1
1%!
1$!
0#!
b0 \
0T
0V
0X
1S
1L
0?
0O
0M
0-
1]
0h
#350000
0'
07
#355000
1'
17
b0 [
b0 g
b0 E
b0 Z
b0 C
b0 B
0q
0n
0m
0,!
0)!
0(!
b11100111 7!
0&!
b0 0
b0 1
0J
b11100111 H
b11100111 I
0Q
0S
0L
0]
#360000
0'
07
#365000
1'
17
#370000
0'
07
#375000
1'
17
b11 )
1:
19
b1100100 D
b1 \
1R
1K
1d
1a
1`
1^
#380000
0'
07
#385000
1'
17
b0 )
0:
09
b0 D
b0 \
0R
0K
0d
0a
0`
0^
b1 [
b1100100 g
b1100100 E
b1 Z
b1 C
b1100100 B
1q
1n
1m
1,!
1)!
1(!
b1001011 7!
1&!
b1100100 0
b1 1
1J
b1001011 H
b1001011 I
1Q
b1 \
#390000
0'
07
#395000
1'
17
1+
1=
b10 \
#400000
0'
07
#405000
1'
17
b10 [
b10 Z
b10 C
b10 1
b11 \
#410000
0'
07
#415000
1'
17
0+
0=
b10 \
b11 \
b11 [
b11 Z
b11 C
b11 1
b100 \
1X
1T
1V
1O
1M
1?
1-
1h
#420000
0'
07
#425000
1'
17
b100 [
b10 k
b100 Z
b100 C
b10 G
b100 1
0%!
b0 \
0T
0V
0X
1S
1L
0?
0O
0M
0-
1]
0h
#430000
0'
07
#435000
1'
17
b0 [
b0 g
b0 E
b0 Z
b0 C
b0 B
0q
0n
0m
0,!
0)!
0(!
b11100111 7!
0&!
b0 0
b0 1
0J
b11100111 H
b11100111 I
0Q
0S
0L
0]
#440000
0'
07
#445000
1'
17
#450000
0'
07
#455000
1'
17
b11 )
1:
19
b1100100 D
b1 \
1R
1K
1d
1a
1`
1^
#460000
0'
07
#465000
1'
17
b0 )
0:
09
b0 D
b0 \
0R
0K
0d
0a
0`
0^
b1 [
b1100100 g
b1100100 E
b1 Z
b1 C
b1100100 B
1q
1n
1m
1,!
1)!
1(!
b1001011 7!
1&!
b1100100 0
b1 1
1J
b1001011 H
b1001011 I
1Q
b1 \
#470000
0'
07
#475000
1'
17
1+
1=
b10 \
#480000
0'
07
#485000
1'
17
b10 [
b10 Z
b10 C
b10 1
b11 \
#490000
0'
07
#495000
1'
17
0+
0=
b10 \
b11 \
b11 [
b11 Z
b11 C
b11 1
b100 \
1X
1T
1V
1O
1M
1?
1-
1h
#500000
0'
07
#505000
1'
17
b100 [
b1 k
b100 Z
b100 C
b1 G
b100 1
1%!
0$!
b0 \
0T
0V
0X
1S
1L
0?
0O
0M
0-
1]
0h
#510000
0'
07
#515000
1'
17
b0 [
b0 g
b0 E
b0 Z
b0 C
b0 B
0q
0n
0m
0,!
0)!
0(!
b11100111 7!
0&!
b0 0
b0 1
0J
b11100111 H
b11100111 I
0Q
0S
0L
0]
#520000
0'
07
#525000
1'
17
#530000
0'
07
#535000
1'
17
b11 )
1:
19
b1100100 D
b1 \
1R
1K
1d
1a
1`
1^
#540000
0'
07
#545000
1'
17
b0 )
0:
09
b0 D
b0 \
0R
0K
0d
0a
0`
0^
b1 [
b1100100 g
b1100100 E
b1 Z
b1 C
b1100100 B
1q
1n
1m
1,!
1)!
1(!
b1001011 7!
1&!
b1100100 0
b1 1
1J
b1001011 H
b1001011 I
1Q
b1 \
#550000
0'
07
#555000
1'
17
1+
1=
b10 \
#560000
0'
07
#565000
1'
17
b10 [
b10 Z
b10 C
b10 1
b11 \
#570000
0'
07
#575000
1'
17
0+
0=
b10 \
b11 \
b11 [
b11 Z
b11 C
b11 1
b100 \
1X
1T
1V
1O
1M
1?
1-
1h
#580000
0'
07
#585000
1'
17
b100 [
b0 k
b100 Z
b100 C
b0 G
b100 1
0%!
0&!
0J
0Q
b0 \
0T
0V
0X
1S
1L
0?
0O
0M
0-
1]
0h
#590000
0'
07
#595000
1'
17
b0 [
b0 g
b0 E
b0 Z
b0 C
b0 B
0q
0n
0m
0,!
0)!
0(!
b11100111 7!
b0 0
b0 1
b11100111 H
b11100111 I
0S
0L
0]
#600000
0'
07
#605000
1'
17
#610000
0'
07
#615000
1'
17
b11 )
1:
19
b1100100 D
b1 \
1R
1K
1d
1a
1`
1^
#620000
0'
07
#625000
1'
17
b0 )
0:
09
b0 D
b0 \
0R
0K
0d
0a
0`
0^
b1 [
b1100100 g
b1100100 E
b1 Z
b1 C
b1100100 B
1q
1n
1m
1,!
1)!
1(!
b1001011 7!
b1100100 0
b1 1
b1001011 H
b1001011 I
b1 \
#630000
0'
07
#635000
1'
17
1+
1=
b10 \
#640000
0'
07
#645000
1'
17
b10 [
b10 Z
b10 C
b10 1
b101 \
#650000
0'
07
#655000
1'
17
0+
0=
b10 \
b101 \
b101 [
b101 Z
b101 C
b101 1
1Y
1U
1V
1O
1N
1@
1.
b1100100 I
#660000
0'
07
#665000
1'
17
b101 6
b1 4
b1 5
b101 4
b101 5
b1100100 A
b1100100 /
#670000
0'
07
#675000
1'
17
1,
1>
b0 \
0U
0V
0Y
1Y
1U
1V
1S
1L
1]
#680000
0'
07
#685000
1'
17
b0 [
b0 g
b0 E
b0 Z
b0 C
b0 B
b0 I
0q
0n
0m
0,!
0)!
0(!
b11100111 7!
b0 0
b0 1
b11100111 H
0S
0U
0V
0Y
0@
0O
0N
0L
b11100111 I
0.
0]
#690000
0'
07
#695000
1'
17
0,
b0 6
