rtl/subtractor.sv
`timescale 1ns / 1ps

module subtractor (
    input  logic [7:0] credit,
    input  logic [7:0] price,
    output logic [7:0] change
);

    assign change = credit - price;

endmodule

rtl/comparator.sv
`timescale 1ns / 1ps

module comparator (
    input  logic [7:0] credit,
    input  logic [7:0] price,
    input  logic [7:0] stock,
    output logic can_sell
);

    assign can_sell = (credit >= price) && (stock > 0);

endmodule

rtl/memory.sv
`timescale 1ns / 1ps

module memory (
    input  logic clk,
    input  logic rst,
    input  logic mem_write,
    input  logic [1:0] sel_item,
    output logic [7:0] price,
    output logic [7:0] stock
);

    logic [7:0] prices_array [0:3];
    logic [7:0] stocks_array [0:3];

    assign price = prices_array[sel_item];
    assign stock = stocks_array[sel_item];

    always_ff @(posedge clk or posedge rst) begin
        if (rst) begin
            prices_array[0] <= 8'd25;  
            stocks_array[0] <= 8'd5;   // 5 unidades de café

            prices_array[1] <= 8'd50;  
            stocks_array[1] <= 8'd5;   // 5 unidade de água

            prices_array[2] <= 8'd75;  
            stocks_array[2] <= 8'd3;   // 3 unidades de suco

            prices_array[3] <= 8'd100; 
            stocks_array[3] <= 8'd2;   // 2 unidades de snack
            
        end else begin
            if (mem_write && stocks_array[sel_item] > 8'd0) begin
                stocks_array[sel_item] <= stocks_array[sel_item] - 8'd1;
            end
        end
    end

endmodule

rtl/credit_reg.sv
`timescale 1ns / 1ps

module credit_reg (
    input  logic clk,
    input  logic rst,
    input  logic clear,
    input  logic credit_load,
    input  logic [7:0] coin_value,
    output logic [7:0] credit
);

    always_ff @(posedge clk or posedge rst) begin
        if (rst) begin
            credit <= 8'b0;
        end else begin
            
            if (clear) begin
                credit <= 8'b0;
            end 
            else if (credit_load) begin
                credit <= credit + coin_value;
            end
        end
    end

endmodule

rtl/control_unit.sv
`timescale 1ns / 1ps

import vending_pkg::*; 

module control_unit (
    input logic clk,
    input logic rst,

    input logic [1:0] coin_in,
    input logic confirm,
    input logic cancel,

    input logic can_sell,

    output logic credit_load,
    output logic clear,
    output logic mem_write,
    output logic sel_change,
    output logic load_change,

    output logic dispense,
    output logic error_out,
    output state_t state_out
);

    state_t current_state, next_state;

    // Transição de estados:
    always_ff @(posedge clk or posedge rst) begin
        if (rst) begin
            current_state <= IDLE;
        end else begin
            current_state <= next_state;
        end
    end

    assign state_out = current_state;

    // Decisão do próximo estado:
    always_comb begin
        next_state = current_state; 

        case (current_state)
            IDLE: begin
                if (coin_in != 2'b00) 
                    next_state = COLLECT;
            end
            
            COLLECT: begin
                if (cancel) 
                    next_state = ERROR;
                else if (confirm) 
                    next_state = CHECK;
            end
            
            CHECK: begin
                if (can_sell) 
                    next_state = DISPENSE;
                else 
                    next_state = ERROR;
            end
            
            DISPENSE: begin
                next_state = CHANGE;
            end
            
            CHANGE: begin
                next_state = IDLE;
            end
            
            ERROR: begin
                if (cancel)
                    next_state = CHANGE;
                else
                    next_state = ERROR;
            end
            
            default: next_state = IDLE;
        endcase
    end

    // Saídas de controle:
    always_comb begin
        credit_load = 1'b0;
        clear = 1'b0;
        mem_write = 1'b0;
        sel_change = 1'b0;
        load_change = 1'b0;
        dispense = 1'b0;
        error_out = 1'b0;

        case (current_state)
            IDLE: begin
                if (coin_in != 2'b00) 
                    credit_load = 1'b1;
            end
            
            COLLECT: begin
                if (coin_in != 2'b00) 
                    credit_load = 1'b1;
            end
            
            CHECK: begin
            end
            
            DISPENSE: begin
                dispense = 1'b1;
                mem_write = 1'b1;
                load_change = 1'b1;
            end
            
            ERROR: begin
                error_out = 1'b1;
                sel_change = 1'b1;
                load_change = 1'b1;
            end
            
            CHANGE: begin
                clear = 1'b1;
            end
        endcase
    end

endmodule

rtl/vending_top.sv
`timescale 1ns / 1ps

import vending_pkg::*;

module vending_top (
    input  logic clk,
    input  logic rst,
    input  logic [1:0] coin_in,
    input  logic [1:0] sel_item,
    input  logic confirm,
    input  logic cancel,

    output logic dispense,
    output logic error_out,
    output logic [7:0] change_out,
    output logic [7:0] display,
    output state_t state_out
);

    logic [7:0] coin_value;
    logic [7:0] credit;
    logic [7:0] price;
    logic [7:0] stock;
    logic [7:0] change_wire;
    logic [7:0] mux_out;

    logic can_sell;
    logic credit_load;
    logic clear;
    logic mem_write;
    logic sel_change;
    logic load_change;

    assign display = credit;

    always_comb begin
        case (coin_in)
            2'b01: coin_value = 8'd25;
            2'b10: coin_value = 8'd50;
            2'b11: coin_value = 8'd100;
            default: coin_value = 8'd0;
        endcase
    end

    assign mux_out = (sel_change) ? credit : change_wire;

    always_ff @(posedge clk or posedge rst) begin
        if (rst) begin
            change_out <= 8'b0;
        end else if (load_change) begin
            change_out <= mux_out;
        end
    end

    control_unit u_fsm (
        .clk (clk),
        .rst (rst),
        .coin_in (coin_in),
        .confirm (confirm),
        .cancel (cancel),
        .can_sell (can_sell),
        .credit_load (credit_load),
        .clear (clear),
        .mem_write (mem_write),
        .sel_change (sel_change),
        .load_change (load_change),
        .dispense (dispense),
        .error_out (error_out),
        .state_out (state_out)
    );

    credit_reg u_credit_reg (
        .clk (clk),
        .rst (rst),
        .clear (clear),
        .credit_load (credit_load),
        .coin_value (coin_value),
        .credit (credit)
    );

    memory u_memory (
        .clk (clk),
        .rst (rst),
        .mem_write (mem_write),
        .sel_item (sel_item),
        .price (price),
        .stock (stock)
    );

    comparator u_comparator (
        .credit (credit),
        .price (price),
        .stock (stock),
        .can_sell (can_sell)
    );

    subtractor u_subtractor (
        .credit (credit),
        .price (price),
        .change (change_wire)
    );

endmodule

sim/tb_vending.sv
`timescale 1ns / 1ps

module vending_tb;

    // Encoding dos estados da FSM:
    localparam ST_IDLE = 3'b000;
    localparam ST_COLLECT = 3'b001;
    localparam ST_CHECK = 3'b010;
    localparam ST_DISPENSE = 3'b011;
    localparam ST_CHANGE = 3'b100;
    localparam ST_ERROR = 3'b101;

    logic clk;
    logic reset;
    logic [1:0] coin_in;
    logic [1:0] sel_item;
    logic confirm;
    logic cancel;

    logic dispense;
    logic error_out;
    logic [7:0] change_out;
    logic [7:0] display;
    logic [2:0] state_out;

    vending_top dut (
        .clk(clk),
        .rst(reset),
        .coin_in(coin_in),
        .sel_item(sel_item),
        .confirm(confirm),
        .cancel(cancel),
        .dispense(dispense),
        .error_out(error_out),
        .change_out(change_out),
        .display(display),
        .state_out(state_out)
    );

    initial begin
        clk = 0;
        forever #5 clk = ~clk;
    end

    initial begin
        #10000;
        $display("[FAIL] A simulacao excedeu 10.000ns, possivel FSM travada");
        $finish;
    end

    task apply_coin(input [1:0] value);
        begin
            @(posedge clk);
            coin_in = value;
            @(posedge clk);
            coin_in = 2'b00;
            @(posedge clk);
        end
    endtask

    task buy_item(input [1:0] item, input [1:0] coins []);
        begin
            foreach (coins[i]) begin
                apply_coin(coins[i]);
            end
            @(posedge clk);
            sel_item = item;
            confirm = 1;
            @(posedge clk);
            confirm = 0;
        end
    endtask

    task check(input [7:0] expected, input [7:0] actual, input string label);
        begin
            if (expected === actual)
                $display("[PASS] %s", label);
            else
                $display("[FAIL] %s | Esperado: %0d, obtido: %0d", label, expected, actual);
        end
    endtask

    task wait_until_state(input [2:0] target_state);
        begin
            while (state_out !== target_state) begin
                @(posedge clk);
            end
        end
    endtask

    task wait_until_idle();
        begin
            wait_until_state(ST_IDLE);
        end
    endtask

    task recover_from_error();
        begin
            @(posedge clk);
            cancel = 1;
            @(posedge clk);
            @(posedge clk);
            cancel = 0;
            
            wait_until_idle();
        end
    endtask

    initial begin
        $dumpfile("vending_tb.vcd");
        $dumpvars(0, vending_tb);

        coin_in = 2'b00;
        sel_item = 2'b00;
        confirm = 0;
        cancel = 0;

        reset = 1;
        repeat (2) @(posedge clk);
        reset = 0;
        wait_until_idle();

        // Cenário 1: compra bem-sucedida com troco:
        buy_item(2'b00, '{2'b11});
        wait_until_state(ST_DISPENSE);
        check(1, dispense, "Cenario 1: dispense = 1");
        wait_until_state(ST_CHANGE);
        check(75, change_out, "Cenario 1: troco = 75");
        wait_until_idle();
        check(0, display, "Cenario 1: credito = 0 ao final");

        // Cenário 2: crédito insuficiente:
        buy_item(2'b11, '{2'b01});
        wait_until_state(ST_ERROR);
        check(1, error_out, "Cenario 2: ERROR = 1");
        check(ST_ERROR, state_out, "Cenario 2: FSM em ERROR");
        recover_from_error();

        // Cenário 3: cancelamento:
        apply_coin(2'b11);
        apply_coin(2'b11);
        @(posedge clk);
        cancel = 1;
        @(posedge clk);
        @(posedge clk);
        cancel = 0;

        wait_until_idle();
        check(200, change_out, "Cenario 3: cancel troco = 200");
        check(0, display, "Cenario 3: credito = 0 apos cancelamento");
        check(ST_IDLE, state_out, "Cenario 3: FSM retorna a IDLE");

        // Cenário 4: estoque zerado:
        for (int i = 1; i <= 4; i++) begin
            buy_item(2'b00, '{2'b11});
            wait_until_idle();
        end
        buy_item(2'b00, '{2'b11});
        wait_until_state(ST_ERROR);
        check(1, error_out, "Cenario 4: ERROR estoque vazio = 1");
        check(ST_ERROR, state_out, "Cenario 4: FSM em ERROR (sem estoque)");
        recover_from_error();

        $display("Todos os cenarios foram validados!");
        $finish;
    end

endmodule

sim/vending_tb.vcd
$date
	Wed Jul  8 19:15:05 2026
$end

$version
	Synopsys VCS version X-2025.06-SP2_Full64
$end

$timescale
	1ps
$end

$comment Csum: 1 a40828043234fe73 $end


$scope module vending_tb $end
$var reg 1 ! clk $end
$var reg 1 " reset $end
$var reg 2 # coin_in [1:0] $end
$var reg 2 $ sel_item [1:0] $end
$var reg 1 % confirm $end
$var reg 1 & cancel $end
$var reg 1 ' dispense $end
$var reg 1 ( error_out $end
$var reg 8 ) change_out [7:0] $end
$var reg 8 * display [7:0] $end
$var reg 3 + state_out [2:0] $end

$scope begin unnamed$$_vcs_2 $end

$scope begin unnamed$$_0 $end
$upscope $end

$upscope $end


$scope begin unnamed$$_vcs_0 $end
$upscope $end


$scope begin unnamed$$_vcs_1 $end
$upscope $end


$scope module dut $end
$var reg 1 , clk $end
$var reg 1 - rst $end
$var reg 2 . coin_in [1:0] $end
$var reg 2 / sel_item [1:0] $end
$var reg 1 0 confirm $end
$var reg 1 1 cancel $end
$var reg 1 2 dispense $end
$var reg 1 3 error_out $end
$var reg 8 4 change_out [7:0] $end
$var reg 8 5 display [7:0] $end
$var reg 3 6 state_out [2:0] $end
$var reg 8 7 coin_value [7:0] $end
$var reg 8 8 credit [7:0] $end
$var reg 8 9 price [7:0] $end
$var reg 8 : stock [7:0] $end
$var reg 8 ; change_wire [7:0] $end
$var reg 8 < mux_out [7:0] $end
$var reg 1 = can_sell $end
$var reg 1 > credit_load $end
$var reg 1 ? clear $end
$var reg 1 @ mem_write $end
$var reg 1 A sel_change $end
$var reg 1 B load_change $end

$scope module u_fsm $end
$var reg 1 C clk $end
$var reg 1 D rst $end
$var reg 2 E coin_in [1:0] $end
$var reg 1 F confirm $end
$var reg 1 G cancel $end
$var reg 1 H can_sell $end
$var reg 1 I credit_load $end
$var reg 1 J clear $end
$var reg 1 K mem_write $end
$var reg 1 L sel_change $end
$var reg 1 M load_change $end
$var reg 1 N dispense $end
$var reg 1 O error_out $end
$var reg 3 P state_out [2:0] $end
$var reg 3 Q current_state [2:0] $end
$var reg 3 R next_state [2:0] $end
$upscope $end


$scope module u_credit_reg $end
$var reg 1 S clk $end
$var reg 1 T rst $end
$var reg 1 U clear $end
$var reg 1 V credit_load $end
$var reg 8 W coin_value [7:0] $end
$var reg 8 X credit [7:0] $end
$upscope $end


$scope module u_memory $end
$var reg 1 Y clk $end
$var reg 1 Z rst $end
$var reg 1 [ mem_write $end
$var reg 2 \ sel_item [1:0] $end
$var reg 8 ] price [7:0] $end
$var reg 8 ^ stock [7:0] $end
$upscope $end


$scope module u_comparator $end
$var reg 8 _ credit [7:0] $end
$var reg 8 ` price [7:0] $end
$var reg 8 a stock [7:0] $end
$var reg 1 b can_sell $end
$upscope $end


$scope module u_subtractor $end
$var reg 8 c credit [7:0] $end
$var reg 8 d price [7:0] $end
$var reg 8 e change [7:0] $end
$upscope $end

$upscope $end

$upscope $end

$enddefinitions $end

#0
$dumpvars
0=
0&
0?
0!
0%
0>
0'
01
00
02
03
0(
0B
0@
1"
1-
0A
0b
0U
0V
1T
0H
0G
0J
0F
0I
0N
0O
0M
0K
1D
0L
0[
1Z
b11100111 e
b00000000 )
b11100111 ;
b00 #
b00000000 7
b00000000 8
b000 Q
b00000000 *
b00000000 4
b00 .
b00000000 5
b00 /
b000 6
b11100111 <
b000 R
b00011001 9
b00 $
b000 +
b00000101 :
b00000000 _
b00011001 `
b00000101 a
b00000000 W
b00000000 X
b00 E
b000 P
b00011001 ]
b00 \
b00000101 ^
b00000000 c
b00011001 d
0,
0C
0Y
0S
$end
#5000
1!
1,
1C
1Y
1S
#10000
0!
0,
0C
0Y
0S
#15000
1!
1,
1C
1Y
1S
0"
0-
0T
0Z
0D
#20000
0!
0,
0C
0Y
0S
#25000
1!
1,
1C
1Y
1S
b11 #
b11 .
b11 E
b01100100 7
b01100100 W
b001 R
1I
1>
1V
#30000
0!
0,
0C
0Y
0S
#35000
1!
1,
1C
1Y
1S
b00 #
b00 .
b00 E
b00000000 7
b00000000 W
b000 R
0I
0>
0V
b001 Q
b001 P
b001 6
b001 +
b01100100 X
b01100100 8
b01100100 c
b01100100 _
b01100100 5
b01100100 *
b001 R
b01001011 e
b01001011 ;
1b
1=
1H
b01001011 <
#40000
0!
0,
0C
0Y
0S
#45000
1!
1,
1C
1Y
1S
#50000
0!
0,
0C
0Y
0S
#55000
1!
1,
1C
1Y
1S
1%
10
1F
b010 R
#60000
0!
0,
0C
0Y
0S
#65000
1!
1,
1C
1Y
1S
0%
00
0F
b001 R
b010 Q
b010 P
b010 6
b010 +
b011 R
#70000
0!
0,
0C
0Y
0S
#75000
1!
1,
1C
1Y
1S
b011 Q
b011 P
b011 6
b011 +
b100 R
1N
12
1'
1M
1B
1K
1@
1[
#80000
0!
0,
0C
0Y
0S
#85000
1!
1,
1C
1Y
1S
b01001011 4
b01001011 )
b100 Q
b100 P
b100 6
b100 +
b00000100 ^
b00000100 :
b00000100 a
b000 R
0N
02
0'
0M
0B
0K
0@
0[
1J
1?
1U
#90000
0!
0,
0C
0Y
0S
#95000
1!
1,
1C
1Y
1S
b000 Q
b000 P
b000 6
b000 +
b00000000 X
b00000000 8
b00000000 c
b00000000 _
b00000000 5
b00000000 *
0J
0?
0U
b11100111 e
b11100111 ;
0b
0=
0H
b11100111 <
#100000
0!
0,
0C
0Y
0S
#105000
1!
1,
1C
1Y
1S
#110000
0!
0,
0C
0Y
0S
#115000
1!
1,
1C
1Y
1S
b01 #
b01 .
b01 E
b00011001 7
b00011001 W
b001 R
1I
1>
1V
#120000
0!
0,
0C
0Y
0S
#125000
1!
1,
1C
1Y
1S
b00 #
b00 .
b00 E
b00000000 7
b00000000 W
b000 R
0I
0>
0V
b001 Q
b001 P
b001 6
b001 +
b00011001 X
b00011001 8
b00011001 c
b00011001 _
b00011001 5
b00011001 *
b001 R
b00000000 e
b00000000 ;
1b
1=
1H
b00000000 <
#130000
0!
0,
0C
0Y
0S
#135000
1!
1,
1C
1Y
1S
#140000
0!
0,
0C
0Y
0S
#145000
1!
1,
1C
1Y
1S
b11 $
b11 /
b11 \
b00000010 ^
b00000010 :
b00000010 a
b01100100 ]
b01100100 9
b01100100 d
b01100100 `
1%
10
1F
b10110101 e
b10110101 ;
0b
0=
0H
b010 R
b10110101 <
#150000
0!
0,
0C
0Y
0S
#155000
1!
1,
1C
1Y
1S
0%
00
0F
b001 R
b010 Q
b010 P
b010 6
b010 +
b101 R
#160000
0!
0,
0C
0Y
0S
#165000
1!
1,
1C
1Y
1S
b101 Q
b101 P
b101 6
b101 +
1O
13
1(
1M
1B
1L
1A
b00011001 <
#170000
0!
0,
0C
0Y
0S
#175000
1!
1,
1C
1Y
1S
b00011001 4
b00011001 )
#180000
0!
0,
0C
0Y
0S
#185000
1!
1,
1C
1Y
1S
1&
11
1G
b100 R
#190000
0!
0,
0C
0Y
0S
#195000
1!
1,
1C
1Y
1S
b100 Q
b100 P
b100 6
b100 +
b000 R
0O
03
0(
0M
0B
0L
0A
1J
1?
1U
b10110101 <
#200000
0!
0,
0C
0Y
0S
#205000
1!
1,
1C
1Y
1S
0&
01
0G
b000 Q
b000 P
b000 6
b000 +
b00000000 X
b00000000 8
b00000000 c
b00000000 _
b00000000 5
b00000000 *
0J
0?
0U
b10011100 e
b10011100 ;
b10011100 <
#210000
0!
0,
0C
0Y
0S
#215000
1!
1,
1C
1Y
1S
#220000
0!
0,
0C
0Y
0S
#225000
1!
1,
1C
1Y
1S
b11 #
b11 .
b11 E
b01100100 7
b01100100 W
b001 R
1I
1>
1V
#230000
0!
0,
0C
0Y
0S
#235000
1!
1,
1C
1Y
1S
b00 #
b00 .
b00 E
b00000000 7
b00000000 W
b000 R
0I
0>
0V
b001 Q
b001 P
b001 6
b001 +
b01100100 X
b01100100 8
b01100100 c
b01100100 _
b01100100 5
b01100100 *
b001 R
b00000000 e
b00000000 ;
1b
1=
1H
b00000000 <
#240000
0!
0,
0C
0Y
0S
#245000
1!
1,
1C
1Y
1S
#250000
0!
0,
0C
0Y
0S
#255000
1!
1,
1C
1Y
1S
b11 #
b11 .
b11 E
b01100100 7
b01100100 W
1I
1>
1V
#260000
0!
0,
0C
0Y
0S
#265000
1!
1,
1C
1Y
1S
b00 #
b00 .
b00 E
b00000000 7
b00000000 W
0I
0>
0V
b11001000 X
b11001000 8
b11001000 c
b11001000 _
b11001000 5
b11001000 *
b01100100 e
b01100100 ;
b01100100 <
#270000
0!
0,
0C
0Y
0S
#275000
1!
1,
1C
1Y
1S
#280000
0!
0,
0C
0Y
0S
#285000
1!
1,
1C
1Y
1S
1&
11
1G
b101 R
#290000
0!
0,
0C
0Y
0S
#295000
1!
1,
1C
1Y
1S
b101 Q
b101 P
b101 6
b101 +
b100 R
1O
13
1(
1M
1B
1L
1A
b11001000 <
#300000
0!
0,
0C
0Y
0S
#305000
1!
1,
1C
1Y
1S
0&
01
0G
b101 R
b11001000 4
b11001000 )
b100 Q
b100 P
b100 6
b100 +
b000 R
0O
03
0(
0M
0B
0L
0A
1J
1?
1U
b01100100 <
#310000
0!
0,
0C
0Y
0S
#315000
1!
1,
1C
1Y
1S
b000 Q
b000 P
b000 6
b000 +
b00000000 X
b00000000 8
b00000000 c
b00000000 _
b00000000 5
b00000000 *
0J
0?
0U
b10011100 e
b10011100 ;
0b
0=
0H
b10011100 <
#320000
0!
0,
0C
0Y
0S
#325000
1!
1,
1C
1Y
1S
#330000
0!
0,
0C
0Y
0S
#335000
1!
1,
1C
1Y
1S
b11 #
b11 .
b11 E
b01100100 7
b01100100 W
b001 R
1I
1>
1V
#340000
0!
0,
0C
0Y
0S
#345000
1!
1,
1C
1Y
1S
b00 #
b00 .
b00 E
b00000000 7
b00000000 W
b000 R
0I
0>
0V
b001 Q
b001 P
b001 6
b001 +
b01100100 X
b01100100 8
b01100100 c
b01100100 _
b01100100 5
b01100100 *
b001 R
b00000000 e
b00000000 ;
1b
1=
1H
b00000000 <
#350000
0!
0,
0C
0Y
0S
#355000
1!
1,
1C
1Y
1S
#360000
0!
0,
0C
0Y
0S
#365000
1!
1,
1C
1Y
1S
b00 $
b00 /
b00 \
b00000100 ^
b00000100 :
b00000100 a
b00011001 ]
b00011001 9
b00011001 d
b00011001 `
1%
10
1F
b01001011 e
b01001011 ;
b010 R
b01001011 <
#370000
0!
0,
0C
0Y
0S
#375000
1!
1,
1C
1Y
1S
0%
00
0F
b001 R
b010 Q
b010 P
b010 6
b010 +
b011 R
#380000
0!
0,
0C
0Y
0S
#385000
1!
1,
1C
1Y
1S
b011 Q
b011 P
b011 6
b011 +
b100 R
1N
12
1'
1M
1B
1K
1@
1[
#390000
0!
0,
0C
0Y
0S
#395000
1!
1,
1C
1Y
1S
b01001011 4
b01001011 )
b100 Q
b100 P
b100 6
b100 +
b00000011 ^
b00000011 :
b00000011 a
b000 R
0N
02
0'
0M
0B
0K
0@
0[
1J
1?
1U
#400000
0!
0,
0C
0Y
0S
#405000
1!
1,
1C
1Y
1S
b000 Q
b000 P
b000 6
b000 +
b00000000 X
b00000000 8
b00000000 c
b00000000 _
b00000000 5
b00000000 *
0J
0?
0U
b11100111 e
b11100111 ;
0b
0=
0H
b11100111 <
#410000
0!
0,
0C
0Y
0S
#415000
1!
1,
1C
1Y
1S
#420000
0!
0,
0C
0Y
0S
#425000
1!
1,
1C
1Y
1S
b11 #
b11 .
b11 E
b01100100 7
b01100100 W
b001 R
1I
1>
1V
#430000
0!
0,
0C
0Y
0S
#435000
1!
1,
1C
1Y
1S
b00 #
b00 .
b00 E
b00000000 7
b00000000 W
b000 R
0I
0>
0V
b001 Q
b001 P
b001 6
b001 +
b01100100 X
b01100100 8
b01100100 c
b01100100 _
b01100100 5
b01100100 *
b001 R
b01001011 e
b01001011 ;
1b
1=
1H
b01001011 <
#440000
0!
0,
0C
0Y
0S
#445000
1!
1,
1C
1Y
1S
#450000
0!
0,
0C
0Y
0S
#455000
1!
1,
1C
1Y
1S
1%
10
1F
b010 R
#460000
0!
0,
0C
0Y
0S
#465000
1!
1,
1C
1Y
1S
0%
00
0F
b001 R
b010 Q
b010 P
b010 6
b010 +
b011 R
#470000
0!
0,
0C
0Y
0S
#475000
1!
1,
1C
1Y
1S
b011 Q
b011 P
b011 6
b011 +
b100 R
1N
12
1'
1M
1B
1K
1@
1[
#480000
0!
0,
0C
0Y
0S
#485000
1!
1,
1C
1Y
1S
b100 Q
b100 P
b100 6
b100 +
b00000010 ^
b00000010 :
b00000010 a
b000 R
0N
02
0'
0M
0B
0K
0@
0[
1J
1?
1U
#490000
0!
0,
0C
0Y
0S
#495000
1!
1,
1C
1Y
1S
b000 Q
b000 P
b000 6
b000 +
b00000000 X
b00000000 8
b00000000 c
b00000000 _
b00000000 5
b00000000 *
0J
0?
0U
b11100111 e
b11100111 ;
0b
0=
0H
b11100111 <
#500000
0!
0,
0C
0Y
0S
#505000
1!
1,
1C
1Y
1S
#510000
0!
0,
0C
0Y
0S
#515000
1!
1,
1C
1Y
1S
b11 #
b11 .
b11 E
b01100100 7
b01100100 W
b001 R
1I
1>
1V
#520000
0!
0,
0C
0Y
0S
#525000
1!
1,
1C
1Y
1S
b00 #
b00 .
b00 E
b00000000 7
b00000000 W
b000 R
0I
0>
0V
b001 Q
b001 P
b001 6
b001 +
b01100100 X
b01100100 8
b01100100 c
b01100100 _
b01100100 5
b01100100 *
b001 R
b01001011 e
b01001011 ;
1b
1=
1H
b01001011 <
#530000
0!
0,
0C
0Y
0S
#535000
1!
1,
1C
1Y
1S
#540000
0!
0,
0C
0Y
0S
#545000
1!
1,
1C
1Y
1S
1%
10
1F
b010 R
#550000
0!
0,
0C
0Y
0S
#555000
1!
1,
1C
1Y
1S
0%
00
0F
b001 R
b010 Q
b010 P
b010 6
b010 +
b011 R
#560000
0!
0,
0C
0Y
0S
#565000
1!
1,
1C
1Y
1S
b011 Q
b011 P
b011 6
b011 +
b100 R
1N
12
1'
1M
1B
1K
1@
1[
#570000
0!
0,
0C
0Y
0S
#575000
1!
1,
1C
1Y
1S
b100 Q
b100 P
b100 6
b100 +
b00000001 ^
b00000001 :
b00000001 a
b000 R
0N
02
0'
0M
0B
0K
0@
0[
1J
1?
1U
#580000
0!
0,
0C
0Y
0S
#585000
1!
1,
1C
1Y
1S
b000 Q
b000 P
b000 6
b000 +
b00000000 X
b00000000 8
b00000000 c
b00000000 _
b00000000 5
b00000000 *
0J
0?
0U
b11100111 e
b11100111 ;
0b
0=
0H
b11100111 <
#590000
0!
0,
0C
0Y
0S
#595000
1!
1,
1C
1Y
1S
#600000
0!
0,
0C
0Y
0S
#605000
1!
1,
1C
1Y
1S
b11 #
b11 .
b11 E
b01100100 7
b01100100 W
b001 R
1I
1>
1V
#610000
0!
0,
0C
0Y
0S
#615000
1!
1,
1C
1Y
1S
b00 #
b00 .
b00 E
b00000000 7
b00000000 W
b000 R
0I
0>
0V
b001 Q
b001 P
b001 6
b001 +
b01100100 X
b01100100 8
b01100100 c
b01100100 _
b01100100 5
b01100100 *
b001 R
b01001011 e
b01001011 ;
1b
1=
1H
b01001011 <
#620000
0!
0,
0C
0Y
0S
#625000
1!
1,
1C
1Y
1S
#630000
0!
0,
0C
0Y
0S
#635000
1!
1,
1C
1Y
1S
1%
10
1F
b010 R
#640000
0!
0,
0C
0Y
0S
#645000
1!
1,
1C
1Y
1S
0%
00
0F
b001 R
b010 Q
b010 P
b010 6
b010 +
b011 R
#650000
0!
0,
0C
0Y
0S
#655000
1!
1,
1C
1Y
1S
b011 Q
b011 P
b011 6
b011 +
b100 R
1N
12
1'
1M
1B
1K
1@
1[
#660000
0!
0,
0C
0Y
0S
#665000
1!
1,
1C
1Y
1S
b100 Q
b100 P
b100 6
b100 +
b00000000 ^
b00000000 :
b00000000 a
b000 R
0N
02
0'
0M
0B
0K
0@
0[
1J
1?
1U
0b
0=
0H
#670000
0!
0,
0C
0Y
0S
#675000
1!
1,
1C
1Y
1S
b000 Q
b000 P
b000 6
b000 +
b00000000 X
b00000000 8
b00000000 c
b00000000 _
b00000000 5
b00000000 *
0J
0?
0U
b11100111 e
b11100111 ;
b11100111 <
#680000
0!
0,
0C
0Y
0S
#685000
1!
1,
1C
1Y
1S
#690000
0!
0,
0C
0Y
0S
#695000
1!
1,
1C
1Y
1S
b11 #
b11 .
b11 E
b01100100 7
b01100100 W
b001 R
1I
1>
1V
#700000
0!
0,
0C
0Y
0S
#705000
1!
1,
1C
1Y
1S
b00 #
b00 .
b00 E
b00000000 7
b00000000 W
b000 R
0I
0>
0V
b001 Q
b001 P
b001 6
b001 +
b01100100 X
b01100100 8
b01100100 c
b01100100 _
b01100100 5
b01100100 *
b001 R
b01001011 e
b01001011 ;
b01001011 <
#710000
0!
0,
0C
0Y
0S
#715000
1!
1,
1C
1Y
1S
#720000
0!
0,
0C
0Y
0S
#725000
1!
1,
1C
1Y
1S
1%
10
1F
b010 R
#730000
0!
0,
0C
0Y
0S
#735000
1!
1,
1C
1Y
1S
0%
00
0F
b001 R
b010 Q
b010 P
b010 6
b010 +
b101 R
#740000
0!
0,
0C
0Y
0S
#745000
1!
1,
1C
1Y
1S
b101 Q
b101 P
b101 6
b101 +
1O
13
1(
1M
1B
1L
1A
b01100100 <
#750000
0!
0,
0C
0Y
0S
#755000
1!
1,
1C
1Y
1S
b01100100 4
b01100100 )
#760000
0!
0,
0C
0Y
0S
#765000
1!
1,
1C
1Y
1S
1&
11
1G
b100 R
#770000
0!
0,
0C
0Y
0S
#775000
1!
1,
1C
1Y
1S
b100 Q
b100 P
b100 6
b100 +
b000 R
0O
03
0(
0M
0B
0L
0A
1J
1?
1U
b01001011 <
#780000
0!
0,
0C
0Y
0S
#785000
1!
1,
1C
1Y
1S
0&
01
0G
b000 Q
b000 P
b000 6
b000 +
b00000000 X
b00000000 8
b00000000 c
b00000000 _
b00000000 5
b00000000 *
0J
0?
0U
b11100111 e
b11100111 ;
b11100111 <
