rtl/subtractor.sv
`timescale 1ns / 1ps

module subtractor (
    input  logic [7:0] credit,
    input  logic [7:0] price,
    output logic [7:0] change
);

    assign change = credit - price;

endmodule

rtl/comparator.sv
`timescale 1ns / 1ps

module comparator (
    input  logic [7:0] credit,
    input  logic [7:0] price,
    input  logic [7:0] stock,
    output logic can_sell
);

    assign can_sell = (credit >= price) && (stock > 0);

endmodule

rtl/memory.sv
`timescale 1ns / 1ps

module memory (
    input  logic clk,
    input  logic rst,
    input  logic mem_write,
    input  logic cancel_collect,
    input  logic [1:0] sel_item,
    output logic [7:0] price,
    output logic [7:0] stock
);

    logic [7:0] prices_array [0:3];
    logic [7:0] stocks_array [0:3];

    assign price = prices_array[sel_item];
    assign stock = stocks_array[sel_item];

    always_ff @(posedge clk or posedge rst) begin
        if (rst) begin
            prices_array[0] <= 8'd25;  
            stocks_array[0] <= 8'd5;   

            prices_array[1] <= 8'd50;  
            stocks_array[1] <= 8'd5;   

            prices_array[2] <= 8'd75;  
            stocks_array[2] <= 8'd3;   

            prices_array[3] <= 8'd100; 
            stocks_array[3] <= 8'd2;   
            
        end else begin
            if (mem_write && stocks_array[sel_item] > 8'd0) begin
                stocks_array[sel_item] <= stocks_array[sel_item] - 8'd1;
            end
            
            if (cancel_collect) begin
                prices_array <= '{default: 8'd0};
            end else begin
            prices_array[0] <= 8'd25;    

            prices_array[1] <= 8'd50;  


            prices_array[2] <= 8'd75;  
  

            prices_array[3] <= 8'd100; 
     
            end
        end
    end

endmodule

rtl/credit_reg.sv
`timescale 1ns / 1ps

module credit_reg (
    input  logic clk,
    input  logic rst,
    input  logic clear,
    input  logic credit_load,
    input  logic [7:0] coin_value,
    output logic [7:0] credit
);

    always_ff @(posedge clk or posedge rst) begin
        if (rst) begin
            credit <= 8'b0;
        end else begin
            
            if (clear) begin
                credit <= 8'b0;
            end 
            else if (credit_load) begin
                credit <= credit + coin_value;
            end
        end
    end

endmodule

rtl/control_unit.sv
`timescale 1ns / 1ps

import vending_pkg::*; 

module control_unit (
    input logic clk,
    input logic rst,

    input logic [1:0] coin_in,
    input logic confirm,
    input logic cancel,

    input logic can_sell,

    output logic credit_load,
    output logic clear,
    output logic mem_write,
    output logic sel_change,
    output logic load_change,
    output logic cancel_collect,
    output logic dispense,
    output logic error_out,
    output state_t state_out
);

    state_t current_state, next_state;

    always_ff @(posedge clk or posedge rst) begin
        if (rst) begin
            current_state <= IDLE;
        end else begin
            current_state <= next_state;
        end
    end

    assign state_out = current_state;

    always_comb begin
        next_state = current_state; 

        case (current_state)
            IDLE: begin
                if (coin_in != 2'b00) 
                    next_state = COLLECT;
            end
            
            COLLECT: begin
                if (cancel) begin
                    next_state = CHANGE;
                end else if (confirm) begin
                    next_state = CHECK;
                end
            end
            
            CHECK: begin
                if (can_sell) 
                    next_state = DISPENSE;
                else 
                    next_state = ERROR;
            end
            
            DISPENSE: begin
                next_state = CHANGE;
            end
            
            CHANGE: begin
                next_state = IDLE;
            end
            
            ERROR: begin
                if (cancel)
                    next_state = IDLE;
                else
                    next_state = ERROR;
            end
            
            default: next_state = IDLE;
        endcase
    end

    always_comb begin
        credit_load    = 1'b0;
        clear          = 1'b0;
        mem_write      = 1'b0;
        sel_change     = 1'b0;
        load_change    = 1'b0;
        cancel_collect = 1'b0;
        dispense       = 1'b0;
        error_out      = 1'b0;

        case (current_state)
            IDLE: begin
                if (coin_in != 2'b00) begin
                    credit_load = 1'b1;
                end
            end
            
            COLLECT: begin
                if (coin_in != 2'b00) begin
                    credit_load = 1'b1;
                end
                if (cancel) begin
                    cancel_collect = 1'b1;
                end
            end
            
            CHECK: begin

            end
            
            DISPENSE: begin
                dispense    = 1'b1;
                mem_write   = 1'b1;
                load_change = 1'b1;
                sel_change  = 1'b0; 
            end
            
            CHANGE: begin
                clear = 1'b1; 
                if (cancel_collect) begin
                    load_change = 1'b1;
                    sel_change  = 1'b1;
                end
            end
            
            ERROR: begin
                error_out   = 1'b1;
                sel_change  = 1'b1; 
                load_change = 1'b1;
                if (cancel) begin
                    clear = 1'b1;
                end
            end
        endcase
    end

endmodule

rtl/vending_top.sv
`timescale 1ns / 1ps

import vending_pkg::*;

module vending_top (
    input  logic clk,
    input  logic rst,
    input  logic [1:0] coin_in,
    input  logic [1:0] sel_item,
    input  logic confirm,
    input  logic cancel,

    output logic dispense,
    output logic error_out,
    output logic [7:0] change_out,
    output logic [7:0] display,
    output state_t state_out
);

    logic [7:0] coin_value;
    logic [7:0] credit;
    logic [7:0] price;
    logic [7:0] stock;
    logic [7:0] change_wire;
    logic [7:0] mux_out;

    logic can_sell;
    logic credit_load;
    logic clear;
    logic mem_write;
    logic sel_change;
    logic load_change;
    logic cancel_collect;

    assign display = credit;

    always_comb begin
        case (coin_in)
            2'b01: coin_value = 8'd25;
            2'b10: coin_value = 8'd50;
            2'b11: coin_value = 8'd100;
            default: coin_value = 8'd0;
        endcase
    end

    
    assign mux_out = (sel_change || state_out == CHANGE && cancel) ? credit : change_wire;

    always_ff @(posedge clk or posedge rst) begin
        if (rst) begin
            change_out <= 8'b0;
        end else if (load_change || (state_out == COLLECT && cancel)) begin
            change_out <= (state_out == COLLECT && cancel) ? credit : mux_out;
        end
    end

    control_unit u_fsm (
        .clk (clk),
        .rst (rst),
        .coin_in (coin_in),
        .confirm (confirm),
        .cancel (cancel),
        .can_sell (can_sell),
        .credit_load (credit_load),
        .clear (clear),
        .mem_write (mem_write),
        .sel_change (sel_change),
        .load_change (load_change),
        .dispense (dispense),
        .error_out (error_out),
        .state_out (state_out),
        .cancel_collect(cancel_collect)
    );

    credit_reg u_credit_reg (
        .clk (clk),
        .rst (rst),
        .clear (clear),
        .credit_load (credit_load),
        .coin_value (coin_value),
        .credit (credit)
    );

    memory u_memory (
        .clk (clk),
        .rst (rst),
        .mem_write (mem_write),
        .sel_item (sel_item),
        .price (price),
        .stock (stock)
    );

    comparator u_comparator (
        .credit (credit),
        .price (price),
        .stock (stock),
        .can_sell (can_sell)
    );

    subtractor u_subtractor (
        .credit (credit),
        .price (price),
        .change (change_wire)
    );

endmodule

sim/tb_vending.sv
`timescale 1ns / 1ps

module vending_tb;

    // Encoding dos estados da FSM:
    localparam ST_IDLE = 3'b000;
    localparam ST_COLLECT = 3'b001;
    localparam ST_CHECK = 3'b010;
    localparam ST_DISPENSE = 3'b011;
    localparam ST_CHANGE = 3'b100;
    localparam ST_ERROR = 3'b101;

    logic clk;
    logic reset;
    logic [1:0] coin_in;
    logic [1:0] sel_item;
    logic confirm;
    logic cancel;

    logic dispense;
    logic error_out;
    logic [7:0] change_out;
    logic [7:0] display;
    logic [2:0] state_out;

    vending_top dut (
        .clk(clk),
        .rst(reset),
        .coin_in(coin_in),
        .sel_item(sel_item),
        .confirm(confirm),
        .cancel(cancel),
        .dispense(dispense),
        .error_out(error_out),
        .change_out(change_out),
        .display(display),
        .state_out(state_out)
    );

    initial begin
        clk = 0;
        forever #5 clk = ~clk;
    end

    initial begin
        #10000;
        $display("[FAIL] A simulacao excedeu 10.000ns, possivel FSM travada");
        $finish;
    end

    task apply_coin(input [1:0] value);
        begin
            @(posedge clk);
            coin_in = value;
            @(posedge clk);
            coin_in = 2'b00;
            @(posedge clk);
        end
    endtask

    task buy_item(input [1:0] item, input [1:0] coins []);
        begin
            sel_item = item;
            foreach (coins[i]) begin
                apply_coin(coins[i]);
            end
            confirm = 1;
            @(posedge clk);
            @(posedge clk);
            confirm = 0;
            @(posedge clk);
        end
    endtask

    task check(input [7:0] expected, input [7:0] actual, input string label);
        begin
            if (expected === actual)
                $display("[PASS] %s", label);
            else
                $display("[FAIL] %s | Esperado: %0d, obtido: %0d", label, expected, actual);
        end
    endtask

    task wait_until_state(input [2:0] target_state);
        begin
            while (state_out !== target_state) begin
                @(posedge clk);
            end
        end
    endtask

    task wait_until_idle();
        begin
            wait_until_state(ST_IDLE);
        end
    endtask

    task recover_from_error();
        begin
            @(posedge clk);
            cancel = 1;
            @(posedge clk);
            @(posedge clk);
            cancel = 0;
            
            wait_until_idle();
        end
    endtask

    initial begin
        $dumpfile("vending_tb.vcd");
        $dumpvars(0, vending_tb);

        coin_in = 2'b00;
        sel_item = 2'b00;
        confirm = 0;
        cancel = 0;

        reset = 1;
        repeat (2) @(posedge clk);
        reset = 0;
        wait_until_idle();

        // Cenário 1: compra bem-sucedida com troco:
        buy_item(2'b00, '{2'b11});
        wait_until_state(ST_DISPENSE);
        check(1, dispense, "Cenario 1: dispense = 1");
        wait_until_state(ST_CHANGE);
        check(75, change_out, "Cenario 1: troco = 75");
        wait_until_idle();
        check(0, display, "Cenario 1: credito = 0 ao final");

        // Cenário 2: crédito insuficiente:
        buy_item(2'b11, '{2'b01});
        wait_until_state(ST_ERROR);
        check(1, error_out, "Cenario 2: ERROR = 1");
        check(ST_ERROR, state_out, "Cenario 2: FSM em ERROR");
        recover_from_error();

        // Cenário 3: cancelamento:
        apply_coin(2'b11);
        apply_coin(2'b11);
        @(posedge clk);
        cancel = 1;
        @(posedge clk);
        @(posedge clk);
        cancel = 0;

        wait_until_idle();
        check(200, change_out, "Cenario 3: cancel troco = 200");
        check(0, display, "Cenario 3: credito = 0 apos cancelamento");
        check(ST_IDLE, state_out, "Cenario 3: FSM retorna a IDLE");

        // Cenário 4: estoque zerado:
        for (int i = 1; i <= 4; i++) begin
            buy_item(2'b00, '{2'b11});
            wait_until_idle();
        end
        buy_item(2'b00, '{2'b11});
        wait_until_state(ST_ERROR);
        check(1, error_out, "Cenario 4: ERROR estoque vazio = 1");
        check(ST_ERROR, state_out, "Cenario 4: FSM em ERROR (sem estoque)");
        recover_from_error();

        $display("Todos os cenarios foram validados!");
        $finish;
    end

endmodule

sim/vending_tb.vcd
$date
	Fri Jul 10 11:19:33 2026
$end

$version
	Synopsys VCS version X-2025.06-SP2_Full64
$end

$timescale
	1ps
$end

$comment Csum: 1 a40828043234fe73 $end


$scope module vending_tb $end
$var reg 1 ! clk $end
$var reg 1 " reset $end
$var reg 2 # coin_in [1:0] $end
$var reg 2 $ sel_item [1:0] $end
$var reg 1 % confirm $end
$var reg 1 & cancel $end
$var reg 1 ' dispense $end
$var reg 1 ( error_out $end
$var reg 8 ) change_out [7:0] $end
$var reg 8 * display [7:0] $end
$var reg 3 + state_out [2:0] $end

$scope begin unnamed$$_vcs_2 $end

$scope begin unnamed$$_0 $end
$upscope $end

$upscope $end


$scope begin unnamed$$_vcs_0 $end
$upscope $end


$scope begin unnamed$$_vcs_1 $end
$upscope $end


$scope module dut $end
$var reg 1 , clk $end
$var reg 1 - rst $end
$var reg 2 . coin_in [1:0] $end
$var reg 2 / sel_item [1:0] $end
$var reg 1 0 confirm $end
$var reg 1 1 cancel $end
$var reg 1 2 dispense $end
$var reg 1 3 error_out $end
$var reg 8 4 change_out [7:0] $end
$var reg 8 5 display [7:0] $end
$var reg 3 6 state_out [2:0] $end
$var reg 8 7 coin_value [7:0] $end
$var reg 8 8 credit [7:0] $end
$var reg 8 9 price [7:0] $end
$var reg 8 : stock [7:0] $end
$var reg 8 ; change_wire [7:0] $end
$var reg 8 < mux_out [7:0] $end
$var reg 1 = can_sell $end
$var reg 1 > credit_load $end
$var reg 1 ? clear $end
$var reg 1 @ mem_write $end
$var reg 1 A sel_change $end
$var reg 1 B load_change $end
$var reg 1 C cancel_collect $end

$scope module u_fsm $end
$var reg 1 D clk $end
$var reg 1 E rst $end
$var reg 2 F coin_in [1:0] $end
$var reg 1 G confirm $end
$var reg 1 H cancel $end
$var reg 1 I can_sell $end
$var reg 1 J credit_load $end
$var reg 1 K clear $end
$var reg 1 L mem_write $end
$var reg 1 M sel_change $end
$var reg 1 N load_change $end
$var reg 1 O cancel_collect $end
$var reg 1 P dispense $end
$var reg 1 Q error_out $end
$var reg 3 R state_out [2:0] $end
$var reg 3 S current_state [2:0] $end
$var reg 3 T next_state [2:0] $end
$upscope $end


$scope module u_credit_reg $end
$var reg 1 U clk $end
$var reg 1 V rst $end
$var reg 1 W clear $end
$var reg 1 X credit_load $end
$var reg 8 Y coin_value [7:0] $end
$var reg 8 Z credit [7:0] $end
$upscope $end


$scope module u_memory $end
$var reg 1 [ clk $end
$var reg 1 \ rst $end
$var reg 1 ] mem_write $end
$var reg 1 ^ cancel_collect $end
$var reg 2 _ sel_item [1:0] $end
$var reg 8 ` price [7:0] $end
$var reg 8 a stock [7:0] $end
$upscope $end


$scope module u_comparator $end
$var reg 8 b credit [7:0] $end
$var reg 8 c price [7:0] $end
$var reg 8 d stock [7:0] $end
$var reg 1 e can_sell $end
$upscope $end


$scope module u_subtractor $end
$var reg 8 f credit [7:0] $end
$var reg 8 g price [7:0] $end
$var reg 8 h change [7:0] $end
$upscope $end

$upscope $end

$upscope $end

$enddefinitions $end

#0
$dumpvars
0=
0&
0C
0?
0!
0%
0>
0'
01
00
02
03
0(
0B
0@
1"
1-
0A
0e
0W
0X
1V
0I
0H
0O
0K
0G
0J
0P
0Q
0N
0L
1E
0M
0^
0]
1\
b11100111 h
b00000000 )
b11100111 ;
b00 #
b00000000 7
b00000000 8
b000 S
b00000000 *
b00000000 4
b00 .
b00000000 5
b00 /
b000 6
b11100111 <
b000 T
b00011001 9
b00 $
b000 +
b00000101 :
b00000000 b
b00011001 c
b00000101 d
b00000000 Y
b00000000 Z
b00 F
b000 R
b00011001 `
b00 _
b00000101 a
b00000000 f
b00011001 g
0,
0D
0[
0U
$end
#5000
1!
1,
1D
1[
1U
#10000
0!
0,
0D
0[
0U
#15000
1!
1,
1D
1[
1U
0"
0-
0V
0\
0E
#20000
0!
0,
0D
0[
0U
#25000
1!
1,
1D
1[
1U
b11 #
b11 .
b11 F
b01100100 7
b01100100 Y
b001 T
1J
1>
1X
#30000
0!
0,
0D
0[
0U
#35000
1!
1,
1D
1[
1U
b00 #
b00 .
b00 F
b00000000 7
b00000000 Y
b000 T
0J
0>
0X
b001 S
b001 R
b001 6
b001 +
b01100100 Z
b01100100 8
b01100100 f
b01100100 b
b01100100 5
b01100100 *
b001 T
b01001011 h
b01001011 ;
1e
1=
1I
b01001011 <
#40000
0!
0,
0D
0[
0U
#45000
1!
1,
1D
1[
1U
1%
10
1G
b010 T
#50000
0!
0,
0D
0[
0U
#55000
1!
1,
1D
1[
1U
b010 S
b010 R
b010 6
b010 +
b011 T
#60000
0!
0,
0D
0[
0U
#65000
1!
1,
1D
1[
1U
0%
00
0G
b011 S
b011 R
b011 6
b011 +
b100 T
1P
12
1'
1N
1B
1L
1@
1]
#70000
0!
0,
0D
0[
0U
#75000
1!
1,
1D
1[
1U
b01001011 4
b01001011 )
b100 S
b100 R
b100 6
b100 +
b00000100 a
b00000100 :
b00000100 d
b000 T
0P
02
0'
0N
0B
0L
0@
0]
1K
1?
1W
#80000
0!
0,
0D
0[
0U
#85000
1!
1,
1D
1[
1U
b000 S
b000 R
b000 6
b000 +
b00000000 Z
b00000000 8
b00000000 f
b00000000 b
b00000000 5
b00000000 *
0K
0?
0W
b11100111 h
b11100111 ;
0e
0=
0I
b11100111 <
#90000
0!
0,
0D
0[
0U
#95000
1!
1,
1D
1[
1U
b11 $
b11 /
b11 _
b00000010 a
b00000010 :
b00000010 d
b01100100 `
b01100100 9
b01100100 g
b01100100 c
b10011100 h
b10011100 ;
b10011100 <
#100000
0!
0,
0D
0[
0U
#105000
1!
1,
1D
1[
1U
b01 #
b01 .
b01 F
b00011001 7
b00011001 Y
b001 T
1J
1>
1X
#110000
0!
0,
0D
0[
0U
#115000
1!
1,
1D
1[
1U
b00 #
b00 .
b00 F
b00000000 7
b00000000 Y
b000 T
0J
0>
0X
b001 S
b001 R
b001 6
b001 +
b00011001 Z
b00011001 8
b00011001 f
b00011001 b
b00011001 5
b00011001 *
b001 T
b10110101 h
b10110101 ;
b10110101 <
#120000
0!
0,
0D
0[
0U
#125000
1!
1,
1D
1[
1U
1%
10
1G
b010 T
#130000
0!
0,
0D
0[
0U
#135000
1!
1,
1D
1[
1U
b010 S
b010 R
b010 6
b010 +
b101 T
#140000
0!
0,
0D
0[
0U
#145000
1!
1,
1D
1[
1U
0%
00
0G
b101 S
b101 R
b101 6
b101 +
1Q
13
1(
1N
1B
1M
1A
b00011001 <
#150000
0!
0,
0D
0[
0U
#155000
1!
1,
1D
1[
1U
b00011001 4
b00011001 )
#160000
0!
0,
0D
0[
0U
#165000
1!
1,
1D
1[
1U
1&
11
1H
b000 T
1K
1?
1W
#170000
0!
0,
0D
0[
0U
#175000
1!
1,
1D
1[
1U
b000 S
b000 R
b000 6
b000 +
b00000000 Z
b00000000 8
b00000000 f
b00000000 b
b00000000 5
b00000000 *
0Q
03
0(
0N
0B
0M
0A
0K
0?
0W
b10011100 h
b10011100 ;
b10011100 <
#180000
0!
0,
0D
0[
0U
#185000
1!
1,
1D
1[
1U
0&
01
0H
#190000
0!
0,
0D
0[
0U
#195000
1!
1,
1D
1[
1U
b11 #
b11 .
b11 F
b01100100 7
b01100100 Y
b001 T
1J
1>
1X
#200000
0!
0,
0D
0[
0U
#205000
1!
1,
1D
1[
1U
b00 #
b00 .
b00 F
b00000000 7
b00000000 Y
b000 T
0J
0>
0X
b001 S
b001 R
b001 6
b001 +
b01100100 Z
b01100100 8
b01100100 f
b01100100 b
b01100100 5
b01100100 *
b001 T
b00000000 h
b00000000 ;
1e
1=
1I
b00000000 <
#210000
0!
0,
0D
0[
0U
#215000
1!
1,
1D
1[
1U
#220000
0!
0,
0D
0[
0U
#225000
1!
1,
1D
1[
1U
b11 #
b11 .
b11 F
b01100100 7
b01100100 Y
1J
1>
1X
#230000
0!
0,
0D
0[
0U
#235000
1!
1,
1D
1[
1U
b00 #
b00 .
b00 F
b00000000 7
b00000000 Y
0J
0>
0X
b11001000 Z
b11001000 8
b11001000 f
b11001000 b
b11001000 5
b11001000 *
b01100100 h
b01100100 ;
b01100100 <
#240000
0!
0,
0D
0[
0U
#245000
1!
1,
1D
1[
1U
#250000
0!
0,
0D
0[
0U
#255000
1!
1,
1D
1[
1U
1&
11
1H
b100 T
1O
1C
1^
b11001000 4
b11001000 )
#260000
0!
0,
0D
0[
0U
#265000
1!
1,
1D
1[
1U
b100 S
b100 R
b100 6
b100 +
b00000000 `
b00000000 9
b00000000 g
b00000000 c
b000 T
0O
0C
0^
1K
1?
1W
b11001000 <
b11001000 h
b11001000 ;
#270000
0!
0,
0D
0[
0U
#275000
1!
1,
1D
1[
1U
0&
01
0H
b000 S
b000 R
b000 6
b000 +
b00000000 Z
b00000000 8
b00000000 f
b00000000 b
b00000000 5
b00000000 *
b01100100 `
b01100100 9
b01100100 g
b01100100 c
0K
0?
0W
b10011100 h
b10011100 ;
0e
0=
0I
b10011100 <
#280000
0!
0,
0D
0[
0U
#285000
1!
1,
1D
1[
1U
b00 $
b00 /
b00 _
b00000100 a
b00000100 :
b00000100 d
b00011001 `
b00011001 9
b00011001 g
b00011001 c
b11100111 h
b11100111 ;
b11100111 <
#290000
0!
0,
0D
0[
0U
#295000
1!
1,
1D
1[
1U
b11 #
b11 .
b11 F
b01100100 7
b01100100 Y
b001 T
1J
1>
1X
#300000
0!
0,
0D
0[
0U
#305000
1!
1,
1D
1[
1U
b00 #
b00 .
b00 F
b00000000 7
b00000000 Y
b000 T
0J
0>
0X
b001 S
b001 R
b001 6
b001 +
b01100100 Z
b01100100 8
b01100100 f
b01100100 b
b01100100 5
b01100100 *
b001 T
b01001011 h
b01001011 ;
1e
1=
1I
b01001011 <
#310000
0!
0,
0D
0[
0U
#315000
1!
1,
1D
1[
1U
1%
10
1G
b010 T
#320000
0!
0,
0D
0[
0U
#325000
1!
1,
1D
1[
1U
b010 S
b010 R
b010 6
b010 +
b011 T
#330000
0!
0,
0D
0[
0U
#335000
1!
1,
1D
1[
1U
0%
00
0G
b011 S
b011 R
b011 6
b011 +
b100 T
1P
12
1'
1N
1B
1L
1@
1]
#340000
0!
0,
0D
0[
0U
#345000
1!
1,
1D
1[
1U
b01001011 4
b01001011 )
b100 S
b100 R
b100 6
b100 +
b00000011 a
b00000011 :
b00000011 d
b000 T
0P
02
0'
0N
0B
0L
0@
0]
1K
1?
1W
#350000
0!
0,
0D
0[
0U
#355000
1!
1,
1D
1[
1U
b000 S
b000 R
b000 6
b000 +
b00000000 Z
b00000000 8
b00000000 f
b00000000 b
b00000000 5
b00000000 *
0K
0?
0W
b11100111 h
b11100111 ;
0e
0=
0I
b11100111 <
#360000
0!
0,
0D
0[
0U
#365000
1!
1,
1D
1[
1U
#370000
0!
0,
0D
0[
0U
#375000
1!
1,
1D
1[
1U
b11 #
b11 .
b11 F
b01100100 7
b01100100 Y
b001 T
1J
1>
1X
#380000
0!
0,
0D
0[
0U
#385000
1!
1,
1D
1[
1U
b00 #
b00 .
b00 F
b00000000 7
b00000000 Y
b000 T
0J
0>
0X
b001 S
b001 R
b001 6
b001 +
b01100100 Z
b01100100 8
b01100100 f
b01100100 b
b01100100 5
b01100100 *
b001 T
b01001011 h
b01001011 ;
1e
1=
1I
b01001011 <
#390000
0!
0,
0D
0[
0U
#395000
1!
1,
1D
1[
1U
1%
10
1G
b010 T
#400000
0!
0,
0D
0[
0U
#405000
1!
1,
1D
1[
1U
b010 S
b010 R
b010 6
b010 +
b011 T
#410000
0!
0,
0D
0[
0U
#415000
1!
1,
1D
1[
1U
0%
00
0G
b011 S
b011 R
b011 6
b011 +
b100 T
1P
12
1'
1N
1B
1L
1@
1]
#420000
0!
0,
0D
0[
0U
#425000
1!
1,
1D
1[
1U
b100 S
b100 R
b100 6
b100 +
b00000010 a
b00000010 :
b00000010 d
b000 T
0P
02
0'
0N
0B
0L
0@
0]
1K
1?
1W
#430000
0!
0,
0D
0[
0U
#435000
1!
1,
1D
1[
1U
b000 S
b000 R
b000 6
b000 +
b00000000 Z
b00000000 8
b00000000 f
b00000000 b
b00000000 5
b00000000 *
0K
0?
0W
b11100111 h
b11100111 ;
0e
0=
0I
b11100111 <
#440000
0!
0,
0D
0[
0U
#445000
1!
1,
1D
1[
1U
#450000
0!
0,
0D
0[
0U
#455000
1!
1,
1D
1[
1U
b11 #
b11 .
b11 F
b01100100 7
b01100100 Y
b001 T
1J
1>
1X
#460000
0!
0,
0D
0[
0U
#465000
1!
1,
1D
1[
1U
b00 #
b00 .
b00 F
b00000000 7
b00000000 Y
b000 T
0J
0>
0X
b001 S
b001 R
b001 6
b001 +
b01100100 Z
b01100100 8
b01100100 f
b01100100 b
b01100100 5
b01100100 *
b001 T
b01001011 h
b01001011 ;
1e
1=
1I
b01001011 <
#470000
0!
0,
0D
0[
0U
#475000
1!
1,
1D
1[
1U
1%
10
1G
b010 T
#480000
0!
0,
0D
0[
0U
#485000
1!
1,
1D
1[
1U
b010 S
b010 R
b010 6
b010 +
b011 T
#490000
0!
0,
0D
0[
0U
#495000
1!
1,
1D
1[
1U
0%
00
0G
b011 S
b011 R
b011 6
b011 +
b100 T
1P
12
1'
1N
1B
1L
1@
1]
#500000
0!
0,
0D
0[
0U
#505000
1!
1,
1D
1[
1U
b100 S
b100 R
b100 6
b100 +
b00000001 a
b00000001 :
b00000001 d
b000 T
0P
02
0'
0N
0B
0L
0@
0]
1K
1?
1W
#510000
0!
0,
0D
0[
0U
#515000
1!
1,
1D
1[
1U
b000 S
b000 R
b000 6
b000 +
b00000000 Z
b00000000 8
b00000000 f
b00000000 b
b00000000 5
b00000000 *
0K
0?
0W
b11100111 h
b11100111 ;
0e
0=
0I
b11100111 <
#520000
0!
0,
0D
0[
0U
#525000
1!
1,
1D
1[
1U
#530000
0!
0,
0D
0[
0U
#535000
1!
1,
1D
1[
1U
b11 #
b11 .
b11 F
b01100100 7
b01100100 Y
b001 T
1J
1>
1X
#540000
0!
0,
0D
0[
0U
#545000
1!
1,
1D
1[
1U
b00 #
b00 .
b00 F
b00000000 7
b00000000 Y
b000 T
0J
0>
0X
b001 S
b001 R
b001 6
b001 +
b01100100 Z
b01100100 8
b01100100 f
b01100100 b
b01100100 5
b01100100 *
b001 T
b01001011 h
b01001011 ;
1e
1=
1I
b01001011 <
#550000
0!
0,
0D
0[
0U
#555000
1!
1,
1D
1[
1U
1%
10
1G
b010 T
#560000
0!
0,
0D
0[
0U
#565000
1!
1,
1D
1[
1U
b010 S
b010 R
b010 6
b010 +
b011 T
#570000
0!
0,
0D
0[
0U
#575000
1!
1,
1D
1[
1U
0%
00
0G
b011 S
b011 R
b011 6
b011 +
b100 T
1P
12
1'
1N
1B
1L
1@
1]
#580000
0!
0,
0D
0[
0U
#585000
1!
1,
1D
1[
1U
b100 S
b100 R
b100 6
b100 +
b00000000 a
b00000000 :
b00000000 d
b000 T
0P
02
0'
0N
0B
0L
0@
0]
1K
1?
1W
0e
0=
0I
#590000
0!
0,
0D
0[
0U
#595000
1!
1,
1D
1[
1U
b000 S
b000 R
b000 6
b000 +
b00000000 Z
b00000000 8
b00000000 f
b00000000 b
b00000000 5
b00000000 *
0K
0?
0W
b11100111 h
b11100111 ;
b11100111 <
#600000
0!
0,
0D
0[
0U
#605000
1!
1,
1D
1[
1U
#610000
0!
0,
0D
0[
0U
#615000
1!
1,
1D
1[
1U
b11 #
b11 .
b11 F
b01100100 7
b01100100 Y
b001 T
1J
1>
1X
#620000
0!
0,
0D
0[
0U
#625000
1!
1,
1D
1[
1U
b00 #
b00 .
b00 F
b00000000 7
b00000000 Y
b000 T
0J
0>
0X
b001 S
b001 R
b001 6
b001 +
b01100100 Z
b01100100 8
b01100100 f
b01100100 b
b01100100 5
b01100100 *
b001 T
b01001011 h
b01001011 ;
b01001011 <
#630000
0!
0,
0D
0[
0U
#635000
1!
1,
1D
1[
1U
1%
10
1G
b010 T
#640000
0!
0,
0D
0[
0U
#645000
1!
1,
1D
1[
1U
b010 S
b010 R
b010 6
b010 +
b101 T
#650000
0!
0,
0D
0[
0U
#655000
1!
1,
1D
1[
1U
0%
00
0G
b101 S
b101 R
b101 6
b101 +
1Q
13
1(
1N
1B
1M
1A
b01100100 <
#660000
0!
0,
0D
0[
0U
#665000
1!
1,
1D
1[
1U
b01100100 4
b01100100 )
#670000
0!
0,
0D
0[
0U
#675000
1!
1,
1D
1[
1U
1&
11
1H
b000 T
1K
1?
1W
#680000
0!
0,
0D
0[
0U
#685000
1!
1,
1D
1[
1U
b000 S
b000 R
b000 6
b000 +
b00000000 Z
b00000000 8
b00000000 f
b00000000 b
b00000000 5
b00000000 *
0Q
03
0(
0N
0B
0M
0A
0K
0?
0W
b11100111 h
b11100111 ;
b11100111 <
#690000
0!
0,
0D
0[
0U
#695000
1!
1,
1D
1[
1U
0&
01
0H
